watson_machine_learning_client/Set.py
watson_machine_learning_client/__init__.py
watson_machine_learning_client/assets.py
watson_machine_learning_client/client.py
watson_machine_learning_client/connections.py
watson_machine_learning_client/deployments.py
watson_machine_learning_client/experiments.py
watson_machine_learning_client/functions.py
watson_machine_learning_client/hpo.py
watson_machine_learning_client/href_definitions.py
watson_machine_learning_client/hw_spec.py
watson_machine_learning_client/instance.py
watson_machine_learning_client/learning_system.py
watson_machine_learning_client/metanames.py
watson_machine_learning_client/model_definition.py
watson_machine_learning_client/models.py
watson_machine_learning_client/pipelines.py
watson_machine_learning_client/pkg_extn.py
watson_machine_learning_client/repository.py
watson_machine_learning_client/runtimes.py
watson_machine_learning_client/script.py
watson_machine_learning_client/shiny.py
watson_machine_learning_client/spaces.py
watson_machine_learning_client/sw_spec.py
watson_machine_learning_client/training.py
watson_machine_learning_client/wml_client_error.py
watson_machine_learning_client/wml_resource.py
watson_machine_learning_client/deployment/__init__.py
watson_machine_learning_client/deployment/base_deployment.py
watson_machine_learning_client/deployment/batch.py
watson_machine_learning_client/deployment/web_service.py
watson_machine_learning_client/experiment/__init__.py
watson_machine_learning_client/experiment/autoai/__init__.py
watson_machine_learning_client/experiment/autoai/autoai.py
watson_machine_learning_client/experiment/autoai/engines/__init__.py
watson_machine_learning_client/experiment/autoai/engines/base_engine.py
watson_machine_learning_client/experiment/autoai/engines/wml_engine.py
watson_machine_learning_client/experiment/autoai/optimizers/__init__.py
watson_machine_learning_client/experiment/autoai/optimizers/base_auto_pipelines.py
watson_machine_learning_client_V4-1.0.135.dist-info/LICENSE.txt
watson_machine_learning_client_V4-1.0.135.dist-info/METADATA
watson_machine_learning_client_V4-1.0.135.dist-info/WHEEL
watson_machine_learning_client_V4-1.0.135.dist-info/top_level.txt
watson_machine_learning_client_V4-1.0.135.dist-info/RECORD
