Metadata-Version: 2.1
Name: watson-machine-learning-client-V4
Version: 1.0.135
Summary: Watson Machine Learning API Client
Home-page: http://wml-api-pyclient-v4.mybluemix.net
Author: IBM
Author-email: svagaral@in.ibm.com, nagiredd@in.ibm.com, amadeusz.masny1@ibm.com
License: BSD
Keywords: watson,machine learning,IBM,Bluemix,client,API,IBM Cloud
Platform: UNKNOWN
Classifier: Development Status :: 4 - Beta
Classifier: Natural Language :: English
Classifier: License :: OSI Approved :: BSD License
Classifier: Programming Language :: Python :: 3.6
Classifier: Operating System :: MacOS :: MacOS X
Classifier: Operating System :: POSIX :: Linux
Classifier: Operating System :: Microsoft :: Windows
Classifier: Intended Audience :: Science/Research
Classifier: Intended Audience :: Developers
Classifier: Intended Audience :: Information Technology
Classifier: Topic :: Software Development :: Libraries
Classifier: Topic :: Software Development :: Libraries :: Python Modules
Classifier: Topic :: Scientific/Engineering :: Artificial Intelligence
Classifier: Topic :: Scientific/Engineering :: Information Analysis
Classifier: Topic :: Internet
Requires-Python: >=3.6
Requires-Dist: requests
Requires-Dist: urllib3
Requires-Dist: pandas (<=1.0.5)
Requires-Dist: certifi
Requires-Dist: lomond
Requires-Dist: tabulate
Requires-Dist: ibm-cos-sdk (==2.7.*)
